ceramic_python/__init__.py
ceramic_python/ceramic_client.py
ceramic_python/did.py
ceramic_python/exceptions.py
ceramic_python/helper.py
ceramic_python/model_instance_document.py
ceramic_python/provider.py
ceramic_python/utils.py
orbis_python/__init__.py
orbis_python/orbis_db.py
ceramicsdk-0.1.4.dist-info/METADATA
ceramicsdk-0.1.4.dist-info/WHEEL
ceramicsdk-0.1.4.dist-info/top_level.txt
ceramicsdk-0.1.4.dist-info/RECORD
