Metadata-Version: 2.1
Name: ceramicsdk
Version: 0.1.4
Summary: This Ceramic client implements the payload building, encoding, and signing needed to interact with the Ceramic Network. It currently supports ModelInstanceDocument and OrbisDB.
Home-page: https://github.com/ceramicstudio/orbis-python-starter/tree/main/py_lib
Author: Ceramic Ecosystem Developers
Classifier: Development Status :: 3 - Alpha
Classifier: Intended Audience :: Developers
Classifier: License :: OSI Approved :: MIT License
Classifier: Programming Language :: Python :: 3
Classifier: Programming Language :: Python :: 3.7
Classifier: Programming Language :: Python :: 3.8
Classifier: Programming Language :: Python :: 3.9
Requires-Python: >=3.7
Requires-Dist: requests ==2.31.0
Requires-Dist: python-dateutil ==2.8.2
Requires-Dist: pytz ==2023.3
Requires-Dist: jsonpatch ==1.33
Requires-Dist: cryptography ==43.0.1
Requires-Dist: jwcrypto ==1.5.0
Requires-Dist: multiformats ==0.3.1
Requires-Dist: dag-cbor ==0.3.3
Requires-Dist: base58 ==2.1.1
Requires-Dist: web3 ==7.2.0
Requires-Dist: cbor2 ==5.6.4
Requires-Dist: bip44 ==0.1.4
Requires-Dist: varint
